{
  "version": "5",
  "dialect": "pg",
  "entries": [
    {
      "idx": 0,
      "version": "5",
      "when": 1701800542437,
      "tag": "0000_solid_star_brand",
      "breakpoints": true
    },
    {
      "idx": 1,
      "version": "5",
      "when": 1701803012885,
      "tag": "0001_woozy_supreme_intelligence",
      "breakpoints": true
    },
    {
      "idx": 2,
      "version": "5",
      "when": 1701804325600,
      "tag": "0002_minor_ikaris",
      "breakpoints": true
    },
    {
      "idx": 3,
      "version": "5",
      "when": 1702987476732,
      "tag": "0003_aromatic_giant_man",
      "breakpoints": true
    }
  ]
}